{
  "updatedAt": "2025-12-16T10:54:53.616Z",
  "services": [
    {
      "id": "site",
      "name": "跨青年 - 网站",
      "url": "https://transyouth.xyz",
      "history": [
        {
          "ts": "2025-12-15T10:57:14.727Z",
          "status": "ok",
          "http": 200,
          "rtt": 210,
          "note": "OK"
        },
        {
          "ts": "2025-12-15T11:27:57.598Z",
          "status": "ok",
          "http": 200,
          "rtt": 246,
          "note": "OK"
        },
        {
          "ts": "2025-12-15T11:44:31.561Z",
          "status": "ok",
          "http": 200,
          "rtt": 172,
          "note": "OK"
        },
        {
          "ts": "2025-12-15T11:56:41.128Z",
          "status": "ok",
          "http": 200,
          "rtt": 175,
          "note": "OK"
        },
        {
          "ts": "2025-12-15T13:03:45.713Z",
          "status": "ok",
          "http": 200,
          "rtt": 238,
          "note": "OK"
        },
        {
          "ts": "2025-12-15T13:49:51.687Z",
          "status": "ok",
          "http": 200,
          "rtt": 187,
          "note": "OK"
        },
        {
          "ts": "2025-12-15T14:16:51.421Z",
          "status": "ok",
          "http": 200,
          "rtt": 184,
          "note": "OK"
        },
        {
          "ts": "2025-12-15T14:49:00.244Z",
          "status": "ok",
          "http": 200,
          "rtt": 164,
          "note": "OK"
        },
        {
          "ts": "2025-12-15T15:14:55.073Z",
          "status": "ok",
          "http": 200,
          "rtt": 159,
          "note": "OK"
        },
        {
          "ts": "2025-12-15T15:43:21.248Z",
          "status": "ok",
          "http": 200,
          "rtt": 224,
          "note": "OK"
        },
        {
          "ts": "2025-12-15T16:00:08.790Z",
          "status": "ok",
          "http": 200,
          "rtt": 233,
          "note": "OK"
        },
        {
          "ts": "2025-12-15T16:45:59.684Z",
          "status": "ok",
          "http": 200,
          "rtt": 255,
          "note": "OK"
        },
        {
          "ts": "2025-12-15T17:14:16.075Z",
          "status": "ok",
          "http": 200,
          "rtt": 405,
          "note": "OK"
        },
        {
          "ts": "2025-12-15T17:43:16.813Z",
          "status": "ok",
          "http": 200,
          "rtt": 264,
          "note": "OK"
        },
        {
          "ts": "2025-12-15T17:57:13.971Z",
          "status": "ok",
          "http": 200,
          "rtt": 210,
          "note": "OK"
        },
        {
          "ts": "2025-12-15T18:44:07.528Z",
          "status": "ok",
          "http": 200,
          "rtt": 227,
          "note": "OK"
        },
        {
          "ts": "2025-12-15T19:02:31.833Z",
          "status": "ok",
          "http": 200,
          "rtt": 186,
          "note": "OK"
        },
        {
          "ts": "2025-12-15T19:29:23.818Z",
          "status": "ok",
          "http": 200,
          "rtt": 228,
          "note": "OK"
        },
        {
          "ts": "2025-12-15T19:44:37.199Z",
          "status": "ok",
          "http": 200,
          "rtt": 212,
          "note": "OK"
        },
        {
          "ts": "2025-12-15T19:57:09.197Z",
          "status": "ok",
          "http": 200,
          "rtt": 251,
          "note": "OK"
        },
        {
          "ts": "2025-12-15T20:33:53.527Z",
          "status": "ok",
          "http": 200,
          "rtt": 273,
          "note": "OK"
        },
        {
          "ts": "2025-12-15T20:52:42.505Z",
          "status": "ok",
          "http": 200,
          "rtt": 191,
          "note": "OK"
        },
        {
          "ts": "2025-12-15T21:18:36.297Z",
          "status": "ok",
          "http": 200,
          "rtt": 186,
          "note": "OK"
        },
        {
          "ts": "2025-12-15T21:39:07.402Z",
          "status": "ok",
          "http": 200,
          "rtt": 189,
          "note": "OK"
        },
        {
          "ts": "2025-12-15T21:51:58.415Z",
          "status": "ok",
          "http": 200,
          "rtt": 218,
          "note": "OK"
        },
        {
          "ts": "2025-12-15T22:17:35.442Z",
          "status": "ok",
          "http": 200,
          "rtt": 230,
          "note": "OK"
        },
        {
          "ts": "2025-12-15T22:40:57.040Z",
          "status": "ok",
          "http": 200,
          "rtt": 236,
          "note": "OK"
        },
        {
          "ts": "2025-12-15T22:54:03.010Z",
          "status": "ok",
          "http": 200,
          "rtt": 196,
          "note": "OK"
        },
        {
          "ts": "2025-12-15T23:22:02.523Z",
          "status": "ok",
          "http": 200,
          "rtt": 236,
          "note": "OK"
        },
        {
          "ts": "2025-12-15T23:40:09.069Z",
          "status": "ok",
          "http": 200,
          "rtt": 251,
          "note": "OK"
        },
        {
          "ts": "2025-12-15T23:52:14.411Z",
          "status": "ok",
          "http": 200,
          "rtt": 168,
          "note": "OK"
        },
        {
          "ts": "2025-12-16T01:24:23.041Z",
          "status": "ok",
          "http": 200,
          "rtt": 215,
          "note": "OK"
        },
        {
          "ts": "2025-12-16T03:11:49.660Z",
          "status": "ok",
          "http": 200,
          "rtt": 280,
          "note": "OK"
        },
        {
          "ts": "2025-12-16T04:06:04.857Z",
          "status": "ok",
          "http": 200,
          "rtt": 208,
          "note": "OK"
        },
        {
          "ts": "2025-12-16T04:47:50.145Z",
          "status": "ok",
          "http": 200,
          "rtt": 184,
          "note": "OK"
        },
        {
          "ts": "2025-12-16T05:12:37.302Z",
          "status": "ok",
          "http": 200,
          "rtt": 194,
          "note": "OK"
        },
        {
          "ts": "2025-12-16T05:41:20.248Z",
          "status": "ok",
          "http": 200,
          "rtt": 339,
          "note": "OK"
        },
        {
          "ts": "2025-12-16T05:55:38.514Z",
          "status": "ok",
          "http": 200,
          "rtt": 166,
          "note": "OK"
        },
        {
          "ts": "2025-12-16T06:42:34.379Z",
          "status": "ok",
          "http": 200,
          "rtt": 185,
          "note": "OK"
        },
        {
          "ts": "2025-12-16T07:02:29.227Z",
          "status": "ok",
          "http": 200,
          "rtt": 160,
          "note": "OK"
        },
        {
          "ts": "2025-12-16T07:32:48.678Z",
          "status": "ok",
          "http": 200,
          "rtt": 243,
          "note": "OK"
        },
        {
          "ts": "2025-12-16T07:48:53.104Z",
          "status": "ok",
          "http": 200,
          "rtt": 210,
          "note": "OK"
        },
        {
          "ts": "2025-12-16T08:15:47.521Z",
          "status": "ok",
          "http": 200,
          "rtt": 198,
          "note": "OK"
        },
        {
          "ts": "2025-12-16T08:48:55.140Z",
          "status": "ok",
          "http": 200,
          "rtt": 228,
          "note": "OK"
        },
        {
          "ts": "2025-12-16T09:15:50.810Z",
          "status": "ok",
          "http": 200,
          "rtt": 226,
          "note": "OK"
        },
        {
          "ts": "2025-12-16T09:43:43.073Z",
          "status": "ok",
          "http": 200,
          "rtt": 373,
          "note": "OK"
        },
        {
          "ts": "2025-12-16T09:57:50.500Z",
          "status": "ok",
          "http": 200,
          "rtt": 300,
          "note": "OK"
        },
        {
          "ts": "2025-12-16T10:35:39.557Z",
          "status": "ok",
          "http": 200,
          "rtt": 186,
          "note": "OK"
        },
        {
          "ts": "2025-12-16T10:54:53.616Z",
          "status": "ok",
          "http": 200,
          "rtt": 147,
          "note": "OK"
        }
      ]
    }
  ]
}