{
  "updatedAt": "2026-04-08T20:26:31.044Z",
  "services": [
    {
      "id": "site",
      "name": "跨青年 - 网站",
      "url": "https://transyouth.xyz",
      "history": [
        {
          "ts": "2026-04-07T21:03:17.538Z",
          "status": "ok",
          "http": 200,
          "rtt": 240,
          "note": "OK"
        },
        {
          "ts": "2026-04-07T21:54:38.540Z",
          "status": "ok",
          "http": 200,
          "rtt": 244,
          "note": "OK"
        },
        {
          "ts": "2026-04-07T22:41:12.602Z",
          "status": "ok",
          "http": 200,
          "rtt": 326,
          "note": "OK"
        },
        {
          "ts": "2026-04-07T23:24:00.308Z",
          "status": "ok",
          "http": 200,
          "rtt": 145,
          "note": "OK"
        },
        {
          "ts": "2026-04-08T00:02:59.101Z",
          "status": "ok",
          "http": 200,
          "rtt": 235,
          "note": "OK"
        },
        {
          "ts": "2026-04-08T03:29:32.155Z",
          "status": "ok",
          "http": 200,
          "rtt": 293,
          "note": "OK"
        },
        {
          "ts": "2026-04-08T05:28:40.468Z",
          "status": "ok",
          "http": 200,
          "rtt": 170,
          "note": "OK"
        },
        {
          "ts": "2026-04-08T06:57:47.415Z",
          "status": "ok",
          "http": 200,
          "rtt": 172,
          "note": "OK"
        },
        {
          "ts": "2026-04-08T08:16:42.877Z",
          "status": "ok",
          "http": 200,
          "rtt": 180,
          "note": "OK"
        },
        {
          "ts": "2026-04-08T09:38:17.414Z",
          "status": "ok",
          "http": 200,
          "rtt": 179,
          "note": "OK"
        },
        {
          "ts": "2026-04-08T10:43:08.089Z",
          "status": "ok",
          "http": 200,
          "rtt": 160,
          "note": "OK"
        },
        {
          "ts": "2026-04-08T11:41:26.415Z",
          "status": "ok",
          "http": 200,
          "rtt": 484,
          "note": "OK"
        },
        {
          "ts": "2026-04-08T12:44:40.217Z",
          "status": "ok",
          "http": 200,
          "rtt": 255,
          "note": "OK"
        },
        {
          "ts": "2026-04-08T14:23:12.170Z",
          "status": "ok",
          "http": 200,
          "rtt": 163,
          "note": "OK"
        },
        {
          "ts": "2026-04-08T15:55:57.803Z",
          "status": "ok",
          "http": 200,
          "rtt": 205,
          "note": "OK"
        },
        {
          "ts": "2026-04-08T17:13:00.311Z",
          "status": "ok",
          "http": 200,
          "rtt": 205,
          "note": "OK"
        },
        {
          "ts": "2026-04-08T18:19:04.276Z",
          "status": "ok",
          "http": 200,
          "rtt": 308,
          "note": "OK"
        },
        {
          "ts": "2026-04-08T19:44:09.905Z",
          "status": "ok",
          "http": 200,
          "rtt": 655,
          "note": "OK"
        },
        {
          "ts": "2026-04-08T20:26:31.044Z",
          "status": "ok",
          "http": 200,
          "rtt": 259,
          "note": "OK"
        }
      ]
    }
  ]
}