{
  "updatedAt": "2026-03-23T10:39:18.204Z",
  "services": [
    {
      "id": "site",
      "name": "跨青年 - 网站",
      "url": "https://transyouth.xyz",
      "history": [
        {
          "ts": "2026-03-22T10:54:20.613Z",
          "status": "ok",
          "http": 200,
          "rtt": 172,
          "note": "OK"
        },
        {
          "ts": "2026-03-22T11:26:31.511Z",
          "status": "ok",
          "http": 200,
          "rtt": 300,
          "note": "OK"
        },
        {
          "ts": "2026-03-22T11:48:45.010Z",
          "status": "ok",
          "http": 200,
          "rtt": 160,
          "note": "OK"
        },
        {
          "ts": "2026-03-22T12:22:45.281Z",
          "status": "ok",
          "http": 200,
          "rtt": 132,
          "note": "OK"
        },
        {
          "ts": "2026-03-22T13:25:49.964Z",
          "status": "ok",
          "http": 200,
          "rtt": 130,
          "note": "OK"
        },
        {
          "ts": "2026-03-22T14:00:13.710Z",
          "status": "ok",
          "http": 200,
          "rtt": 192,
          "note": "OK"
        },
        {
          "ts": "2026-03-22T14:40:00.180Z",
          "status": "ok",
          "http": 200,
          "rtt": 147,
          "note": "OK"
        },
        {
          "ts": "2026-03-22T15:00:22.754Z",
          "status": "ok",
          "http": 200,
          "rtt": 208,
          "note": "OK"
        },
        {
          "ts": "2026-03-22T15:36:52.956Z",
          "status": "ok",
          "http": 200,
          "rtt": 140,
          "note": "OK"
        },
        {
          "ts": "2026-03-22T15:57:01.695Z",
          "status": "ok",
          "http": 200,
          "rtt": 170,
          "note": "OK"
        },
        {
          "ts": "2026-03-22T16:40:54.318Z",
          "status": "ok",
          "http": 200,
          "rtt": 170,
          "note": "OK"
        },
        {
          "ts": "2026-03-22T17:02:18.129Z",
          "status": "ok",
          "http": 200,
          "rtt": 176,
          "note": "OK"
        },
        {
          "ts": "2026-03-22T17:37:30.855Z",
          "status": "ok",
          "http": 200,
          "rtt": 139,
          "note": "OK"
        },
        {
          "ts": "2026-03-22T17:57:40.734Z",
          "status": "ok",
          "http": 200,
          "rtt": 222,
          "note": "OK"
        },
        {
          "ts": "2026-03-22T18:50:59.659Z",
          "status": "ok",
          "http": 200,
          "rtt": 199,
          "note": "OK"
        },
        {
          "ts": "2026-03-22T19:20:39.798Z",
          "status": "ok",
          "http": 200,
          "rtt": 200,
          "note": "OK"
        },
        {
          "ts": "2026-03-22T19:44:16.337Z",
          "status": "ok",
          "http": 200,
          "rtt": 188,
          "note": "OK"
        },
        {
          "ts": "2026-03-22T19:58:41.098Z",
          "status": "ok",
          "http": 200,
          "rtt": 184,
          "note": "OK"
        },
        {
          "ts": "2026-03-22T20:39:14.313Z",
          "status": "ok",
          "http": 200,
          "rtt": 189,
          "note": "OK"
        },
        {
          "ts": "2026-03-22T21:00:28.619Z",
          "status": "ok",
          "http": 200,
          "rtt": 167,
          "note": "OK"
        },
        {
          "ts": "2026-03-22T21:36:41.062Z",
          "status": "ok",
          "http": 200,
          "rtt": 257,
          "note": "OK"
        },
        {
          "ts": "2026-03-22T21:57:22.410Z",
          "status": "ok",
          "http": 200,
          "rtt": 202,
          "note": "OK"
        },
        {
          "ts": "2026-03-22T22:36:04.659Z",
          "status": "ok",
          "http": 200,
          "rtt": 163,
          "note": "OK"
        },
        {
          "ts": "2026-03-22T22:59:03.647Z",
          "status": "ok",
          "http": 200,
          "rtt": 192,
          "note": "OK"
        },
        {
          "ts": "2026-03-22T23:38:10.099Z",
          "status": "ok",
          "http": 200,
          "rtt": 212,
          "note": "OK"
        },
        {
          "ts": "2026-03-23T00:00:17.935Z",
          "status": "ok",
          "http": 200,
          "rtt": 233,
          "note": "OK"
        },
        {
          "ts": "2026-03-23T03:19:51.885Z",
          "status": "ok",
          "http": 200,
          "rtt": 149,
          "note": "OK"
        },
        {
          "ts": "2026-03-23T05:18:09.503Z",
          "status": "ok",
          "http": 200,
          "rtt": 187,
          "note": "OK"
        },
        {
          "ts": "2026-03-23T06:43:15.280Z",
          "status": "ok",
          "http": 200,
          "rtt": 192,
          "note": "OK"
        },
        {
          "ts": "2026-03-23T07:49:29.601Z",
          "status": "ok",
          "http": 200,
          "rtt": 232,
          "note": "OK"
        },
        {
          "ts": "2026-03-23T08:43:00.614Z",
          "status": "ok",
          "http": 200,
          "rtt": 155,
          "note": "OK"
        },
        {
          "ts": "2026-03-23T09:47:01.376Z",
          "status": "ok",
          "http": 200,
          "rtt": 312,
          "note": "OK"
        },
        {
          "ts": "2026-03-23T10:39:18.204Z",
          "status": "ok",
          "http": 200,
          "rtt": 214,
          "note": "OK"
        }
      ]
    }
  ]
}